flaskws/__init__.py
flaskws/client.py
flaskws/defs.py
flaskws/protocol.py
flaskws/utils.py
flaskws/ws.py
flaskws/wsgi.py
flaskws/wssock.py
flaskws/wstornado.py
flaskws/wsuwsgi.py
flaskws3-3.0.4.1.dist-info/LICENSE
flaskws3-3.0.4.1.dist-info/METADATA
flaskws3-3.0.4.1.dist-info/WHEEL
flaskws3-3.0.4.1.dist-info/top_level.txt
flaskws3-3.0.4.1.dist-info/RECORD
