Metadata-Version: 2.1
Name: flaskws3
Version: 3.0.4.1
Summary: WebSockets for Flask.
Home-page: https://github.com/RixInGithub/flaskws3
Author: RixTheTyrunt
Author-email: rixthetyrunt@gmail.com
License-File: LICENSE
Requires-Dist: flask
Requires-Dist: tornado
